migro/__init__.py
migro/cli.py
migro/settings.py
migro/filestack/__init__.py
migro/filestack/utils.py
migro/uploader/__init__.py
migro/uploader/utils.py
migro/uploader/worker.py
tests/__init__.py
tests/conftest.py
tests/test_uploader.py
uploadcare_migro-1.8.0.dist-info/LICENSE
uploadcare_migro-1.8.0.dist-info/METADATA
uploadcare_migro-1.8.0.dist-info/WHEEL
uploadcare_migro-1.8.0.dist-info/entry_points.txt
uploadcare_migro-1.8.0.dist-info/top_level.txt
uploadcare_migro-1.8.0.dist-info/RECORD
