Metadata-Version: 2.1
Name: uploadcare-migro
Version: 1.8.0
Summary: Uploadcare migration tool
Home-page: https://github.com/uploadcare/migro
Author: Uploadcare team
Author-email: hello@uploadcare.com
License: MIT
Platform: UNKNOWN
Classifier: Development Status :: 5 - Production/Stable
Classifier: Environment :: Web Environment
Classifier: Intended Audience :: Developers
Classifier: License :: OSI Approved :: MIT License
Classifier: Operating System :: OS Independent
Classifier: Programming Language :: Python
Classifier: Programming Language :: Python :: 3.8
Classifier: Programming Language :: Python :: 3.9
Classifier: Programming Language :: Python :: 3.10
License-File: LICENSE
Requires-Dist: aiohttp (==3.8.1)
Requires-Dist: click (==8.1.3)
Requires-Dist: colorama (==0.4.4)
Requires-Dist: python-dateutil (==2.8.2)
Requires-Dist: tqdm (==4.64.0)
